LICENCE.md
README.md
setup.cfg
setup.py
steamlib/__init__.py
steamlib/client.py
steamlib/confirmation.py
steamlib/exceptions.py
steamlib/guard.py
steamlib/login.py
steamlib/market.py
steamlib/models.py
steamlib/trade.py
steamlib/utils.py
steamlib.egg-info/PKG-INFO
steamlib.egg-info/SOURCES.txt
steamlib.egg-info/dependency_links.txt
steamlib.egg-info/requires.txt
steamlib.egg-info/top_level.txt